Trackrefiner/__init__.py
Trackrefiner/bacteriaTrackEditor.py
Trackrefiner/cli.py
Trackrefiner/gui.py
Trackrefiner/logo.png
Trackrefiner/core/__init__.py
Trackrefiner/core/correction/__init__.py
Trackrefiner/core/correction/findFixTrackingErrors.py
Trackrefiner/core/correction/action/__init__.py
Trackrefiner/core/correction/action/bacteriaTrackingUpdate.py
Trackrefiner/core/correction/action/candidateBacteriaFeatureSpace.py
Trackrefiner/core/correction/action/checkValidity.py
Trackrefiner/core/correction/action/drawDistributionPlot.py
Trackrefiner/core/correction/action/findOutlier.py
Trackrefiner/core/correction/action/generateLogFile.py
Trackrefiner/core/correction/action/helper.py
Trackrefiner/core/correction/action/neighborAnalysis.py
Trackrefiner/core/correction/action/propagateBacteriaLabels.py
Trackrefiner/core/correction/action/regionOfInterestFilter.py
Trackrefiner/core/correction/action/featuresCalculation/__init__.py
Trackrefiner/core/correction/action/featuresCalculation/calcElongationRate.py
Trackrefiner/core/correction/action/featuresCalculation/calcVelocity.py
Trackrefiner/core/correction/action/featuresCalculation/calculateOverlap.py
Trackrefiner/core/correction/action/featuresCalculation/fluorescenceIntensity.py
Trackrefiner/core/correction/action/trackingCost/__init__.py
Trackrefiner/core/correction/action/trackingCost/calculateCreateLinkCost.py
Trackrefiner/core/correction/action/trackingCost/calculateCreateLinkCostMCC.py
Trackrefiner/core/correction/action/trackingCost/calculateCreateLinkCostUB.py
Trackrefiner/core/correction/action/trackingCost/calculateCreateLinkCostUE.py
Trackrefiner/core/correction/action/trackingCost/calculateInitialCostTerms.py
Trackrefiner/core/correction/action/trackingCost/calculateMaintainingLinkCost.py
Trackrefiner/core/correction/action/trackingCost/evaluateDivisionLinkForUB.py
Trackrefiner/core/correction/modelTraning/__init__.py
Trackrefiner/core/correction/modelTraning/bacterialBehaviorModelTraining.py
trackrefiner-1.3.dist-info/METADATA
trackrefiner-1.3.dist-info/WHEEL
trackrefiner-1.3.dist-info/entry_points.txt
trackrefiner-1.3.dist-info/top_level.txt
trackrefiner-1.3.dist-info/RECORD
